litq/__init__.py
tests/__init__.py
litq-0.1.0.dist-info/METADATA
litq-0.1.0.dist-info/WHEEL
litq-0.1.0.dist-info/entry_points.txt
litq-0.1.0.dist-info/licenses/LICENSE
litq-0.1.0.dist-info/RECORD
