Metadata-Version: 2.1
Name: litq
Version: 0.1.0
Summary: >> Off process queue with sqlite <<
Project-URL: Homepage, https://github.com/rednafi/rubric
Project-URL: Issue Tracker, https://github.com/pypa/rubric/issues
Author-email: rednafi <redowan.nafi@gmail.com>
License: Copyright (c) 2022-2022 Redowan Delowar and others
Classifier: Intended Audience :: Developers
Classifier: License :: OSI Approved :: MIT License
Classifier: Natural Language :: English
Classifier: Operating System :: OS Independent
Classifier: Programming Language :: Python
Classifier: Programming Language :: Python :: 3.10
Classifier: Programming Language :: Python :: 3.11
Classifier: Programming Language :: Python :: 3.8
Classifier: Programming Language :: Python :: 3.9
Classifier: Programming Language :: Python :: Implementation :: CPython
Classifier: Topic :: Software Development :: Libraries :: Python Modules
Requires-Python: >=3.8
Requires-Dist: click
Provides-Extra: dev
Requires-Dist: black; extra == 'dev'
Requires-Dist: build; extra == 'dev'
Requires-Dist: flake8; extra == 'dev'
Requires-Dist: hatch; extra == 'dev'
Requires-Dist: isort; extra == 'dev'
Requires-Dist: mypy; extra == 'dev'
Requires-Dist: pip-tools; extra == 'dev'
Requires-Dist: pre-commit; extra == 'dev'
Requires-Dist: pytest; extra == 'dev'
Requires-Dist: twine; extra == 'dev'
Requires-Dist: types-pkg-resources; extra == 'dev'
Requires-Dist: types-setuptools; extra == 'dev'
